{
  "config": {
    "arch": "kmd2",
    "no_conv": true,
    "slot_ortho": 0.0,
    "r": 1,
    "heads": 4,
    "dk": 32,
    "dv": 32,
    "d": 128,
    "layers": 2,
    "eps": 0.5,
    "kron": false,
    "compact_P": 0,
    "compact_R": 8,
    "compact_ste": false,
    "trap": true,
    "slow_decay": 0.97,
    "n_pairs": 16,
    "n_query": 4,
    "keys_vocab": 128,
    "vals_vocab": 64,
    "batch": 32,
    "steps": 6000,
    "lr": 0.001,
    "eval_every": 1000,
    "seed": 0,
    "device": "cuda:1",
    "out": "research/runs_fable/tr_np16_noconv_trap.json"
  },
  "n_params": 677128,
  "curve": {
    "0": {
      "tok_acc": 0.0088,
      "recall": 0.0,
      "ce": 5.3917
    },
    "1000": {
      "tok_acc": 0.127,
      "recall": 0.0,
      "ce": 3.1096
    },
    "2000": {
      "tok_acc": 0.1025,
      "recall": 0.0,
      "ce": 2.996
    },
    "3000": {
      "tok_acc": 0.1045,
      "recall": 0.0,
      "ce": 2.9383
    },
    "4000": {
      "tok_acc": 0.1016,
      "recall": 0.0,
      "ce": 2.8237
    },
    "5000": {
      "tok_acc": 0.1113,
      "recall": 0.0,
      "ce": 2.8671
    },
    "5999": {
      "tok_acc": 0.1025,
      "recall": 0.0,
      "ce": 2.7027
    }
  },
  "final_tokacc": 0.1025,
  "final_recall": 0.0,
  "wall_s": 343.0
}